README.md
setup.cfg
setup.py
versioneer.py
PropertyBackendApiClient/ApiClient.py
PropertyBackendApiClient/Exceptions.py
PropertyBackendApiClient/LoginSession.py
PropertyBackendApiClient/VerboseLoggingOutputFilteredClass.py
PropertyBackendApiClient/Workflows.py
PropertyBackendApiClient/__init__.py
PropertyBackendApiClient/_version.py
PropertyBackendApiClient.egg-info/PKG-INFO
PropertyBackendApiClient.egg-info/SOURCES.txt
PropertyBackendApiClient.egg-info/dependency_links.txt
PropertyBackendApiClient.egg-info/not-zip-safe
PropertyBackendApiClient.egg-info/requires.txt
PropertyBackendApiClient.egg-info/top_level.txt
PropertyBackendApiClient/Types/UserObj.py
PropertyBackendApiClient/Types/__init__.py